{
  "source_workbook": "C:\\Users\\Administrator\\Downloads\\storyboard_ep1_timing_adjusted.xlsx",
  "sheets": [
    {
      "title": "第1集分镜表",
      "rows": 63,
      "cols": 14,
      "header": [
        "分组",
        "15秒段",
        "镜头号",
        "时长(s)",
        "起始时间",
        "结束时间",
        "场景/时间",
        "镜头景别",
        "镜头运动",
        "画面内容",
        "人物动作/神态",
        "台词对白",
        "角色",
        "音效"
      ],
      "data": [
        {
          "分组": "第1组",
          "15秒段": "0-16.5秒",
          "镜头号": 1,
          "时长(s)": 1.4,
          "起始时间": 0,
          "结束时间": 1.4,
          "场景/时间": "1-1 日 / 外 / 京都湖面上",
          "镜头景别": "大全景",
          "镜头运动": "航拍俯拍+缓慢下摇",
          "画面内容": "小雨拍打湖面，京都湖面上漂着不少游湖画舫，色彩缤纷，层层铺开。",
          "人物动作/神态": "各家貌美的千金贵女分散坐于不同画舫，满是期待地环顾四周，建立“赏湖等人”的群像气氛。",
          "台词对白": "—",
          "角色": "贵女群像",
          "音效": "雨声、湖水声、远处丝竹声"
        },
        {
          "分组": "第1组",
          "15秒段": "0-16.5秒",
          "镜头号": 2,
          "时长(s)": 0.9,
          "起始时间": 1.4,
          "结束时间": 2.3,
          "场景/时间": "1-1 日 / 外 / 京都湖面上",
          "镜头景别": "中远景",
          "镜头运动": "横向平移掠镜",
          "画面内容": "镜头掠过一艘艘画舫，衣香鬓影与湖面涟漪交错。",
          "人物动作/神态": "贵女们或执扇、或探身张望，彼此用眼神交换期待，节奏轻快地铺出“众人都在等同一个人”。",
          "台词对白": "—",
          "角色": "贵女群像",
          "音效": "船橹划水声、低声议论"
        },
        {
          "分组": "第1组",
          "15秒段": "0-16.5秒",
          "镜头号": 3,
          "时长(s)": 1.8,
          "起始时间": 2.3,
          "结束时间": 4.1,
          "场景/时间": "1-1 日 / 外 / 京都湖面上",
          "镜头景别": "中近景",
          "镜头运动": "微推",
          "画面内容": "定到一位神情羞怯的贵女，背景仍见雨幕与船檐。",
          "人物动作/神态": "贵女甲面颊微红，试探般望向湖面尽头，语气羞涩带期待。",
          "台词对白": "贵女甲（害羞）：不知那位公子何时会来？",
          "角色": "贵女甲",
          "音效": "环境雨声稍压低，留对白空间"
        },
        {
          "分组": "第1组",
          "15秒段": "0-16.5秒",
          "镜头号": 4,
          "时长(s)": 0.9,
          "起始时间": 4.1,
          "结束时间": 5,
          "场景/时间": "1-1 日 / 外 / 李娇娇所在画舫",
          "镜头景别": "中景",
          "镜头运动": "切入定镜",
          "画面内容": "切到其中一艘画舫，一袭青衫的李娇娇趴在船边。",
          "人物动作/神态": "李娇娇郑重地看着湖面，与周围少女怀春的氛围形成反差。",
          "台词对白": "—",
          "角色": "李娇娇",
          "音效": "船身轻晃声"
        },
        {
          "分组": "第1组",
          "15秒段": "0-16.5秒",
          "镜头号": 5,
          "时长(s)": 1.1,
          "起始时间": 5,
          "结束时间": 6.1,
          "场景/时间": "1-1 日 / 外 / 李娇娇所在画舫",
          "镜头景别": "近景",
          "镜头运动": "俯角定镜",
          "画面内容": "镜头压到船边与湖面，雨点砸出密集水纹。",
          "人物动作/神态": "李娇娇视线死死盯住湖面，像是在认真判断“跳下去”的可行性。",
          "台词对白": "—",
          "角色": "李娇娇",
          "音效": "雨点打水声加强"
        },
        {
          "分组": "第1组",
          "15秒段": "0-16.5秒",
          "镜头号": 6,
          "时长(s)": 2.4,
          "起始时间": 6.1,
          "结束时间": 8.5,
          "场景/时间": "1-1 日 / 外 / 李娇娇所在画舫",
          "镜头景别": "近特写",
          "镜头运动": "微推到眼神",
          "画面内容": "李娇娇侧脸贴近画面，湖面反光映在眼里，形成轻微冷调。",
          "人物动作/神态": "她眼神郑重得近乎荒诞，内心冒出求生欲与逃离欲并存的念头。",
          "台词对白": "李娇娇（OS）：跳湖自尽就能回家了吧？",
          "角色": "李娇娇",
          "音效": "环境声抽离，内心OS入场"
        },
        {
          "分组": "第1组",
          "15秒段": "0-16.5秒",
          "镜头号": 7,
          "时长(s)": 0.7,
          "起始时间": 8.5,
          "结束时间": 9.2,
          "场景/时间": "1-1 日 / 外 / 李娇娇主观意识",
          "镜头景别": "插入特写",
          "镜头运动": "快切+轻微震动",
          "画面内容": "意识空间中红色警报图形一闪，像在脑海里直接炸开。",
          "人物动作/神态": "“李娇娇脑中警报声直响”以视觉化方式呈现，为系统出现做预告。",
          "台词对白": "—",
          "角色": "系统（画外）/李娇娇",
          "音效": "电子警报“滴——滴——”"
        },
        {
          "分组": "第1组",
          "15秒段": "0-16.5秒",
          "镜头号": 8,
          "时长(s)": 4.2,
          "起始时间": 9.2,
          "结束时间": 13.4,
          "场景/时间": "1-1 日 / 外 / 李娇娇所在画舫",
          "镜头景别": "近特写",
          "镜头运动": "定镜+微震",
          "画面内容": "李娇娇表情一僵，脑内提示几乎盖过环境画面。",
          "人物动作/神态": "系统强势切入，冷硬的规训感打断她的“跳湖”计划，镜头不切，靠声音压迫制造戏剧点。",
          "台词对白": "系统：警告！请宿主杜绝自杀想法，未完成任务之前，躯体死亡，宿主也将永远消失。",
          "角色": "系统",
          "音效": "电子警报、系统女声/机械声"
        },
        {
          "分组": "第1组",
          "15秒段": "0-16.5秒",
          "镜头号": 9,
          "时长(s)": 1.1,
          "起始时间": 13.4,
          "结束时间": 14.5,
          "场景/时间": "1-1 日 / 外 / 李娇娇所在画舫",
          "镜头景别": "近景",
          "镜头运动": "反应切",
          "画面内容": "警报落下后，李娇娇面部肌肉迅速垮掉。",
          "人物动作/神态": "她翻了个白眼，委屈地憋着气，整个人像被现实狠狠干回船上。",
          "台词对白": "—",
          "角色": "李娇娇",
          "音效": "警报尾音消失，留轻微哼唧"
        },
        {
          "分组": "第1组",
          "15秒段": "0-16.5秒",
          "镜头号": 10,
          "时长(s)": 2,
          "起始时间": 14.5,
          "结束时间": 16.5,
          "场景/时间": "1-1 日 / 外 / 李娇娇所在画舫",
          "镜头景别": "中近景",
          "镜头运动": "小幅跟摇",
          "画面内容": "镜头跟着她的肩膀动作轻晃，带出一点短剧喜感。",
          "人物动作/神态": "李娇娇气鼓鼓地握着拳头朝空中挥舞，委屈、烦躁又无可奈何。",
          "台词对白": "—",
          "角色": "李娇娇",
          "音效": "衣料摩擦声、短促哼唧"
        },
        {
          "分组": "第2组",
          "15秒段": "16.5-33.1秒",
          "镜头号": 11,
          "时长(s)": 0.8,
          "起始时间": 16.5,
          "结束时间": 17.3,
          "场景/时间": "1-1 日 / 外 / 李娇娇所在画舫",
          "镜头景别": "中近景",
          "镜头运动": "定镜",
          "画面内容": "承接上一镜，李娇娇还维持着挥拳后的姿势。",
          "人物动作/神态": "她鼻子一皱，整个人委屈得像要当场控诉命运，给长OS起情绪起点。",
          "台词对白": "—",
          "角色": "李娇娇",
          "音效": "环境声回归"
        },
        {
          "分组": "第2组",
          "15秒段": "16.5-33.1秒",
          "镜头号": 12,
          "时长(s)": 7.2,
          "起始时间": 17.3,
          "结束时间": 24.5,
          "场景/时间": "1-1 日 / 外 / 湖面与意识蒙太奇",
          "镜头景别": "多景别蒙太奇",
          "镜头运动": "跳切+叠化+书页闪回",
          "画面内容": "快速切李娇娇、雨湖、翻动的书页、《阴阳师》字样意象、炮灰女配命运感画面，再闪过段青莲的危险剪影。",
          "人物动作/神态": "用高密度蒙太奇承载信息量：一觉醒来穿书、同名同姓炮灰女配、系统任务离谱，节奏要快但信息清楚。",
          "台词对白": "李娇娇（OS）：救命啊！一觉醒来，我发现自己穿进了《阴阳师》这本玄幻小说。更离谱的是，我成了书中那个与我同名同姓的炮灰女配！系统给的任务简直有大病，让我把那个阴鹜偏执、杀人如麻的病娇反派段青莲，拉回“正道”？",
          "角色": "李娇娇",
          "音效": "OS持续，书页翻动声、低频鼓点垫底"
        },
        {
          "分组": "第2组",
          "15秒段": "16.5-33.1秒",
          "镜头号": 13,
          "时长(s)": 0.7,
          "起始时间": 24.5,
          "结束时间": 25.2,
          "场景/时间": "1-1 日 / 外 / 湖面群船",
          "镜头景别": "远景",
          "镜头运动": "切回群像",
          "画面内容": "不远处画舫忽然炸开骚动，众人视线齐齐朝同一方向集中。",
          "人物动作/神态": "贵女们激动尖叫，情绪瞬间从等待切成“目标出现”的亢奋。",
          "台词对白": "—",
          "角色": "贵女群像",
          "音效": "少女尖叫声骤起"
        },
        {
          "分组": "第2组",
          "15秒段": "16.5-33.1秒",
          "镜头号": 14,
          "时长(s)": 2,
          "起始时间": 25.2,
          "结束时间": 27.2,
          "场景/时间": "1-1 日 / 外 / 某画舫",
          "镜头景别": "近景",
          "镜头运动": "快推",
          "画面内容": "镜头猛推到先前的贵女甲脸上。",
          "人物动作/神态": "她几乎按捺不住激动，探身报信，带动全场节奏提速。",
          "台词对白": "贵女甲：来了来了！沈家的船来了！",
          "角色": "贵女甲",
          "音效": "人声沸起"
        },
        {
          "分组": "第2组",
          "15秒段": "16.5-33.1秒",
          "镜头号": 15,
          "时长(s)": 0.8,
          "起始时间": 27.2,
          "结束时间": 28,
          "场景/时间": "1-1 日 / 外 / 李娇娇所在画舫",
          "镜头景别": "中景",
          "镜头运动": "起身跟拍",
          "画面内容": "李娇娇闻言立即从船边弹起。",
          "人物动作/神态": "她的状态从吐槽模式切入警惕模式，抬眼锁定远处动静。",
          "台词对白": "—",
          "角色": "李娇娇",
          "音效": "船板踩踏声"
        },
        {
          "分组": "第2组",
          "15秒段": "16.5-33.1秒",
          "镜头号": 16,
          "时长(s)": 1.4,
          "起始时间": 28,
          "结束时间": 29.4,
          "场景/时间": "1-1 日 / 外 / 李娇娇主观视角",
          "镜头景别": "主观远景",
          "镜头运动": "穿雨微推",
          "画面内容": "李娇娇隔着细雨望向远处，水雾中一艘更醒目的游舫正逼近。",
          "人物动作/神态": "镜头通过轻推和雨幕遮挡制造“重要人物登场前”的悬念感。",
          "台词对白": "—",
          "角色": "李娇娇",
          "音效": "雨声、船橹切水声渐近"
        },
        {
          "分组": "第2组",
          "15秒段": "16.5-33.1秒",
          "镜头号": 17,
          "时长(s)": 1.5,
          "起始时间": 29.4,
          "结束时间": 30.9,
          "场景/时间": "1-1 日 / 外 / 沈家赤木游舫",
          "镜头景别": "全景",
          "镜头运动": "迎面推进",
          "画面内容": "一艘极为精致的赤木游舫驶来，船体纹理、饰件与其他船只拉开等级差。",
          "人物动作/神态": "船头破开湖面，视觉上明确“沈家的船”就是本场焦点。",
          "台词对白": "—",
          "角色": "段青莲/沈云书",
          "音效": "船体破水声、气氛音乐抬升"
        },
        {
          "分组": "第2组",
          "15秒段": "16.5-33.1秒",
          "镜头号": 18,
          "时长(s)": 1,
          "起始时间": 30.9,
          "结束时间": 31.9,
          "场景/时间": "1-1 日 / 外 / 沈家赤木游舫",
          "镜头景别": "中景",
          "镜头运动": "横移定住",
          "画面内容": "船上的段青莲乌发白衣，懒散地倚在船柱旁，带着几分阴柔的美。",
          "人物动作/神态": "镜头从衣袍横移到面容，既展示俊美，也埋下危险反差。",
          "台词对白": "—",
          "角色": "段青莲",
          "音效": "丝竹声停一拍，留人物出场感"
        },
        {
          "分组": "第2组",
          "15秒段": "16.5-33.1秒",
          "镜头号": 19,
          "时长(s)": 0.7,
          "起始时间": 31.9,
          "结束时间": 32.6,
          "场景/时间": "1-1 日 / 外 / 沈家赤木游舫",
          "镜头景别": "中近景",
          "镜头运动": "切特写",
          "画面内容": "坐在段青莲旁边、穿着粉红贵服的沈云书正痴痴地看着他。",
          "人物动作/神态": "沈云书目光黏在段青莲身上，先行建立她的迷恋与占有欲。",
          "台词对白": "—",
          "角色": "沈云书",
          "音效": "轻柔衣料声"
        },
        {
          "分组": "第2组",
          "15秒段": "16.5-33.1秒",
          "镜头号": 20,
          "时长(s)": 0.5,
          "起始时间": 32.6,
          "结束时间": 33.1,
          "场景/时间": "1-1 日 / 外 / 李娇娇所在画舫",
          "镜头景别": "近景",
          "镜头运动": "反应切",
          "画面内容": "切回李娇娇，眼神明显一紧。",
          "人物动作/神态": "她对“攻略对象”与“疯批反派”的现实登场产生本能警戒。",
          "台词对白": "—",
          "角色": "李娇娇",
          "音效": "气氛乐暗压"
        },
        {
          "分组": "第3组",
          "15秒段": "33.1-48.7秒",
          "镜头号": 21,
          "时长(s)": 1,
          "起始时间": 33.1,
          "结束时间": 34.1,
          "场景/时间": "1-1 日 / 外 / 沈家赤木游舫",
          "镜头景别": "中近景",
          "镜头运动": "微推",
          "画面内容": "镜头再次吃到段青莲正脸：乌发白衣、面容英俊，柔美里带着不好接近的锋利。",
          "人物动作/神态": "用二次确认镜头强调：这个人外形“柔弱”，但气场并不柔弱。",
          "台词对白": "—",
          "角色": "段青莲",
          "音效": "低频氛围音"
        },
        {
          "分组": "第3组",
          "15秒段": "33.1-48.7秒",
          "镜头号": 22,
          "时长(s)": 0.8,
          "起始时间": 34.1,
          "结束时间": 34.9,
          "场景/时间": "1-1 日 / 外 / 沈家赤木游舫",
          "镜头景别": "双人中景",
          "镜头运动": "定镜",
          "画面内容": "段青莲倚柱不动，沈云书坐在旁边，痴痴地望着他。",
          "人物动作/神态": "人物关系在同框中被清楚建立：她主动、他被追逐，但掌控权未必在她手里。",
          "台词对白": "—",
          "角色": "段青莲/沈云书",
          "音效": "湖面环境声"
        },
        {
          "分组": "第3组",
          "15秒段": "33.1-48.7秒",
          "镜头号": 23,
          "时长(s)": 2.8,
          "起始时间": 34.9,
          "结束时间": 37.7,
          "场景/时间": "1-1 日 / 外 / 李娇娇主观意识",
          "镜头景别": "插入特写",
          "镜头运动": "HUD叠加+轻震",
          "画面内容": "李娇娇的视野边缘像被系统界面覆盖，目标锁定到段青莲身上。",
          "人物动作/神态": "系统正式宣布“攻略对象”已出现，开启任务主线，镜头要有明显的任务触发感。",
          "台词对白": "系统：攻略对象段青莲已出现，各项指标已开启，祝宿主好运。",
          "角色": "系统",
          "音效": "电子提示音、界面开启声"
        },
        {
          "分组": "第3组",
          "15秒段": "33.1-48.7秒",
          "镜头号": 24,
          "时长(s)": 0.8,
          "起始时间": 37.7,
          "结束时间": 38.5,
          "场景/时间": "1-1 日 / 外 / 李娇娇所在画舫",
          "镜头景别": "近景",
          "镜头运动": "突推",
          "画面内容": "李娇娇听到提示后，本能瞪大眼睛。",
          "人物动作/神态": "她对系统口中的关键对象与眼前这张脸之间的反差，第一时间是不敢信。",
          "台词对白": "—",
          "角色": "李娇娇",
          "音效": "短促吸气声"
        },
        {
          "分组": "第3组",
          "15秒段": "33.1-48.7秒",
          "镜头号": 25,
          "时长(s)": 2.6,
          "起始时间": 38.5,
          "结束时间": 41.1,
          "场景/时间": "1-1 日 / 外 / 李娇娇所在画舫",
          "镜头景别": "近特写",
          "镜头运动": "定镜",
          "画面内容": "镜头压在李娇娇眼神与嘴角的微妙变化上，让观众完整接收她的判断。",
          "人物动作/神态": "她盯着段青莲，震惊里夹着怀疑，语气近乎吐槽。",
          "台词对白": "李娇娇（惊诧OS）：这个柔弱的男人竟是杀人如麻的疯批反派？",
          "角色": "李娇娇",
          "音效": "OS入场，背景声微降"
        },
        {
          "分组": "第3组",
          "15秒段": "33.1-48.7秒",
          "镜头号": 26,
          "时长(s)": 1.2,
          "起始时间": 41.1,
          "结束时间": 42.3,
          "场景/时间": "1-1 日 / 外 / 沈家赤木游舫",
          "镜头景别": "中近景",
          "镜头运动": "望向反打",
          "画面内容": "段青莲注意到李娇娇的注视，转头朝她看去，侧头温柔含笑。",
          "人物动作/神态": "这一笑既有礼也有危险，像是无意，但已经把主动权拿回自己手里。",
          "台词对白": "—",
          "角色": "段青莲",
          "音效": "气氛乐轻轻上扬"
        },
        {
          "分组": "第3组",
          "15秒段": "33.1-48.7秒",
          "镜头号": 27,
          "时长(s)": 1.6,
          "起始时间": 42.3,
          "结束时间": 43.9,
          "场景/时间": "1-1 日 / 外 / 沈家赤木游舫",
          "镜头景别": "双人近景",
          "镜头运动": "小幅摇镜",
          "画面内容": "沈云书看到两人对视，立刻不满地拉住段青莲的胳膊撒娇。",
          "人物动作/神态": "她动作急而亲昵，明显在用身体语言夺回段青莲的注意力。",
          "台词对白": "—",
          "角色": "沈云书/段青莲",
          "音效": "衣袖摩擦声"
        },
        {
          "分组": "第3组",
          "15秒段": "33.1-48.7秒",
          "镜头号": 28,
          "时长(s)": 0.8,
          "起始时间": 43.9,
          "结束时间": 44.7,
          "场景/时间": "1-1 日 / 外 / 沈家赤木游舫",
          "镜头景别": "过肩近景",
          "镜头运动": "压迫式反打",
          "画面内容": "从沈云书肩后看向段青莲，李娇娇被隔在视线之外。",
          "人物动作/神态": "镜头让“第三人目光”被物理打断，强化沈云书的占有姿态。",
          "台词对白": "—",
          "角色": "沈云书/段青莲",
          "音效": "人群窃语"
        },
        {
          "分组": "第3组",
          "15秒段": "33.1-48.7秒",
          "镜头号": 29,
          "时长(s)": 2.2,
          "起始时间": 44.7,
          "结束时间": 46.9,
          "场景/时间": "1-1 日 / 外 / 沈家赤木游舫",
          "镜头景别": "中近景",
          "镜头运动": "微推",
          "画面内容": "沈云书几乎贴着段青莲，带着醋意与撒娇问责。",
          "人物动作/神态": "语气甜、占有欲却锋利，是她对李娇娇视线的直接回击。",
          "台词对白": "沈云书：段公子！今日你是来陪我游湖的？怎可将目光分给她人？",
          "角色": "沈云书",
          "音效": "娇嗔语气、环境声压低"
        },
        {
          "分组": "第3组",
          "15秒段": "33.1-48.7秒",
          "镜头号": 30,
          "时长(s)": 1.8,
          "起始时间": 46.9,
          "结束时间": 48.7,
          "场景/时间": "1-1 日 / 外 / 沈家赤木游舫",
          "镜头景别": "近特写",
          "镜头运动": "定格式停顿",
          "画面内容": "段青莲唇角缓缓勾起，眼底却看不透。",
          "人物动作/神态": "这一记邪魅一笑是他接下来的“调情反杀”前置停顿，给下组动作留钩子。",
          "台词对白": "—",
          "角色": "段青莲",
          "音效": "低频音一压"
        },
        {
          "分组": "第4组",
          "15秒段": "48.7-64.2秒",
          "镜头号": 31,
          "时长(s)": 0.8,
          "起始时间": 48.7,
          "结束时间": 49.5,
          "场景/时间": "1-1 日 / 外 / 沈家赤木游舫",
          "镜头景别": "中景",
          "镜头运动": "突切+抬镜",
          "画面内容": "段青莲突然出手，一个公主抱将沈云书抱起。",
          "人物动作/神态": "动作来得极快，瞬间打破方才的“言语撒娇”，把暧昧推进到肢体层面。",
          "台词对白": "—",
          "角色": "段青莲/沈云书",
          "音效": "衣袍翻动声"
        },
        {
          "分组": "第4组",
          "15秒段": "48.7-64.2秒",
          "镜头号": 32,
          "时长(s)": 1,
          "起始时间": 49.5,
          "结束时间": 50.5,
          "场景/时间": "1-1 日 / 外 / 沈家赤木游舫",
          "镜头景别": "全景",
          "镜头运动": "环绕半圈",
          "画面内容": "段青莲抱着沈云书转体一圈，船身与湖面在背景里旋出眩晕感。",
          "人物动作/神态": "沈云书下意识搂住他，整个人被这记强势回应击中。",
          "台词对白": "—",
          "角色": "段青莲/沈云书",
          "音效": "人群惊呼、衣摆破风声"
        },
        {
          "分组": "第4组",
          "15秒段": "48.7-64.2秒",
          "镜头号": 33,
          "时长(s)": 1.2,
          "起始时间": 50.5,
          "结束时间": 51.7,
          "场景/时间": "1-1 日 / 外 / 湖面群船",
          "镜头景别": "群像中景",
          "镜头运动": "插切群像反应",
          "画面内容": "四周画舫上的贵女们有人捂脸、有人睁大眼、有人暗暗吃醋。",
          "人物动作/神态": "把“众人观看”的公共性拍出来，既烘托禁忌感，也加重李娇娇的吐槽合理性。",
          "台词对白": "—",
          "角色": "贵女群像",
          "音效": "惊呼、低低抽气"
        },
        {
          "分组": "第4组",
          "15秒段": "48.7-64.2秒",
          "镜头号": 34,
          "时长(s)": 2,
          "起始时间": 51.7,
          "结束时间": 53.7,
          "场景/时间": "1-1 日 / 外 / 沈家赤木游舫",
          "镜头景别": "正反打特写",
          "镜头运动": "缓推到极近",
          "画面内容": "段青莲俊朗邪魅的脸贴近沈云书，几乎贴着她的嘴唇；沈云书满脸通红，面带笑意。",
          "人物动作/神态": "镜头严格按“正反打特写”执行，利用嘴唇距离制造强烈张力。",
          "台词对白": "—",
          "角色": "段青莲/沈云书",
          "音效": "呼吸声、环境音压到最低"
        },
        {
          "分组": "第4组",
          "15秒段": "48.7-64.2秒",
          "镜头号": 35,
          "时长(s)": 2.4,
          "起始时间": 53.7,
          "结束时间": 56.1,
          "场景/时间": "1-1 日 / 外 / 沈家赤木游舫",
          "镜头景别": "特写",
          "镜头运动": "缓推停在嘴边",
          "画面内容": "段青莲近距离低声开口，表情从温柔滑入邪气。",
          "人物动作/神态": "对白要轻，但压迫感足，让“陪”字带出玩弄意味。",
          "台词对白": "段青莲：如何陪？这样可好？",
          "角色": "段青莲",
          "音效": "低声对白、心跳式鼓点"
        },
        {
          "分组": "第4组",
          "15秒段": "48.7-64.2秒",
          "镜头号": 36,
          "时长(s)": 1.2,
          "起始时间": 56.1,
          "结束时间": 57.3,
          "场景/时间": "1-1 日 / 外 / 沈家赤木游舫",
          "镜头景别": "中近景",
          "镜头运动": "锁定",
          "画面内容": "沈云书一脸害羞地看着段青莲，顺势抱住他。",
          "人物动作/神态": "她明显被撩动，自以为掌控局面，情绪全在脸上。",
          "台词对白": "—",
          "角色": "沈云书/段青莲",
          "音效": "衣料轻擦声"
        },
        {
          "分组": "第4组",
          "15秒段": "48.7-64.2秒",
          "镜头号": 37,
          "时长(s)": 1.2,
          "起始时间": 57.3,
          "结束时间": 58.5,
          "场景/时间": "1-1 日 / 外 / 湖面群船",
          "镜头景别": "群像远中景",
          "镜头运动": "横向平移",
          "画面内容": "再扫一遍湖面船舫上的贵女：有人捂脸害羞，有人吃醋，有人偷看。",
          "人物动作/神态": "群像反应持续抬高场面热度，让暧昧成为全湖都在围观的事件。",
          "台词对白": "—",
          "角色": "贵女群像",
          "音效": "议论声、扇面摩擦声"
        },
        {
          "分组": "第4组",
          "15秒段": "48.7-64.2秒",
          "镜头号": 38,
          "时长(s)": 0.8,
          "起始时间": 58.5,
          "结束时间": 59.3,
          "场景/时间": "1-1 日 / 外 / 李娇娇所在画舫",
          "镜头景别": "近景",
          "镜头运动": "切回反应",
          "画面内容": "李娇娇见状立马转身，不去看两人。",
          "人物动作/神态": "她对眼前“大庭广众亲密戏”本能排斥，动作干脆带喜剧点。",
          "台词对白": "—",
          "角色": "李娇娇",
          "音效": "转身衣摆声"
        },
        {
          "分组": "第4组",
          "15秒段": "48.7-64.2秒",
          "镜头号": 39,
          "时长(s)": 2.6,
          "起始时间": 59.3,
          "结束时间": 61.9,
          "场景/时间": "1-1 日 / 外 / 李娇娇所在画舫",
          "镜头景别": "近特写",
          "镜头运动": "吐槽式定镜",
          "画面内容": "李娇娇背对热闹，脸上写满嫌弃和不可思议。",
          "人物动作/神态": "吐槽要快、准、狠，像替观众把心里话说出来。",
          "台词对白": "李娇娇（嫌弃）：系统你确定我穿的不是禁书吗？大庭广众之下，竟然行不轨之事！",
          "角色": "李娇娇",
          "音效": "OS/对白突出，环境声退后"
        },
        {
          "分组": "第4组",
          "15秒段": "48.7-64.2秒",
          "镜头号": 40,
          "时长(s)": 2.3,
          "起始时间": 61.9,
          "结束时间": 64.2,
          "场景/时间": "1-1 日 / 外 / 李娇娇主观意识",
          "镜头景别": "插入特写",
          "镜头运动": "电子弹窗式切入",
          "画面内容": "系统提示像弹窗一样挤进画面，打断她的吐槽。",
          "人物动作/神态": "机械回应一本正经，反衬李娇娇吐槽的荒诞感。",
          "台词对白": "系统：请宿主清除脑中黄色废料，本系统不支持穿禁书！",
          "角色": "系统",
          "音效": "电子提示音、系统声"
        },
        {
          "分组": "第5组",
          "15秒段": "64.2-81.2秒",
          "镜头号": 41,
          "时长(s)": 0.8,
          "起始时间": 64.2,
          "结束时间": 65,
          "场景/时间": "1-1 日 / 外 / 沈家赤木游舫",
          "镜头景别": "近景",
          "镜头运动": "插入",
          "画面内容": "切回段青莲怀中的沈云书，她的手已探向他的衣襟。",
          "人物动作/神态": "动作带着主动试探与占有冲动，节奏要紧接上句系统吐槽形成反差笑点。",
          "台词对白": "—",
          "角色": "沈云书/段青莲",
          "音效": "衣料拉扯声"
        },
        {
          "分组": "第5组",
          "15秒段": "64.2-81.2秒",
          "镜头号": 42,
          "时长(s)": 1.1,
          "起始时间": 65,
          "结束时间": 66.1,
          "场景/时间": "1-1 日 / 外 / 沈家赤木游舫",
          "镜头景别": "特写",
          "镜头运动": "慢推",
          "画面内容": "沈云书扯开段青莲胸口的衣衫，白衣松散，露出线条分明的胸肌。",
          "人物动作/神态": "动作不必色情化拍摄，重点是“她在众目睽睽下进一步越界”。",
          "台词对白": "—",
          "角色": "沈云书/段青莲",
          "音效": "布料撕扯/滑落声"
        },
        {
          "分组": "第5组",
          "15秒段": "64.2-81.2秒",
          "镜头号": 43,
          "时长(s)": 3.8,
          "起始时间": 66.1,
          "结束时间": 69.9,
          "场景/时间": "1-1 日 / 外 / 沈家赤木游舫",
          "镜头景别": "中近景",
          "镜头运动": "正拍微推",
          "画面内容": "沈云书仰头望着段青莲，说话时目光从脸滑到胸口，再回到眼睛。",
          "人物动作/神态": "她语气迷恋又自信，几乎把“独占”两个字写在神态里。",
          "台词对白": "沈云书：段公子生的如此俊美，不知令多少佳人神魂颠倒。可惜，如此郎君，只我一人配独享。",
          "角色": "沈云书",
          "音效": "语气暧昧，环境声压低"
        },
        {
          "分组": "第5组",
          "15秒段": "64.2-81.2秒",
          "镜头号": 44,
          "时长(s)": 0.8,
          "起始时间": 69.9,
          "结束时间": 70.7,
          "场景/时间": "1-1 日 / 外 / 沈家赤木游舫",
          "镜头景别": "近景",
          "镜头运动": "反打定格",
          "画面内容": "段青莲只是看着她，笑容邪魅。",
          "人物动作/神态": "他笑得配合，却没有把真情绪给出来，危险感在笑里隐隐浮现。",
          "台词对白": "—",
          "角色": "段青莲",
          "音效": "低频音垫一下"
        },
        {
          "分组": "第5组",
          "15秒段": "64.2-81.2秒",
          "镜头号": 45,
          "时长(s)": 3.4,
          "起始时间": 70.7,
          "结束时间": 74.1,
          "场景/时间": "1-1 日 / 外 / 沈家赤木游舫",
          "镜头景别": "中近景",
          "镜头运动": "微推",
          "画面内容": "段青莲终于开口，语气轻描淡写，却把话题直接切回交易。",
          "人物动作/神态": "从暧昧转利益，人物冷硬底色第一次被明确露出。",
          "台词对白": "段青莲：我只同意陪你游船，而且，你答应我的往生木何时给我。",
          "角色": "段青莲",
          "音效": "对白清晰、气氛转冷"
        },
        {
          "分组": "第5组",
          "15秒段": "64.2-81.2秒",
          "镜头号": 46,
          "时长(s)": 1.1,
          "起始时间": 74.1,
          "结束时间": 75.2,
          "场景/时间": "1-1 日 / 外 / 沈家赤木游舫",
          "镜头景别": "近景",
          "镜头运动": "柔焦切入",
          "画面内容": "沈云书面露桃花，芊芊玉手拿起一杯酒。",
          "人物动作/神态": "她完全没把危险听进去，反而把这一刻理解成更深一步的挑逗邀请。",
          "台词对白": "—",
          "角色": "沈云书",
          "音效": "酒液轻晃声"
        },
        {
          "分组": "第5组",
          "15秒段": "64.2-81.2秒",
          "镜头号": 47,
          "时长(s)": 1.3,
          "起始时间": 75.2,
          "结束时间": 76.5,
          "场景/时间": "1-1 日 / 外 / 沈家赤木游舫",
          "镜头景别": "特写",
          "镜头运动": "慢动作插入",
          "画面内容": "杯口倾斜，酒液沿着段青莲健壮的胸肌流下，形成极具冲击力的视觉插入。",
          "人物动作/神态": "这一镜要短促有力，服务“全场已经越界”的感受，不停留、不渲染过度。",
          "台词对白": "—",
          "角色": "沈云书/段青莲",
          "音效": "酒液倾倒声"
        },
        {
          "分组": "第5组",
          "15秒段": "64.2-81.2秒",
          "镜头号": 48,
          "时长(s)": 1.1,
          "起始时间": 76.5,
          "结束时间": 77.6,
          "场景/时间": "1-1 日 / 外 / 沈家赤木游舫",
          "镜头景别": "双人近景",
          "镜头运动": "低机位缓推",
          "画面内容": "沈云书抬眸望着段青莲，眼里满是势在必得的痴迷。",
          "人物动作/神态": "段青莲站位更高，虽被撩拨包围，却始终像一头被逼到发笑的危险兽。",
          "台词对白": "—",
          "角色": "沈云书/段青莲",
          "音效": "呼吸声、雨声远化"
        },
        {
          "分组": "第5组",
          "15秒段": "64.2-81.2秒",
          "镜头号": 49,
          "时长(s)": 2.7,
          "起始时间": 77.6,
          "结束时间": 80.3,
          "场景/时间": "1-1 日 / 外 / 沈家赤木游舫",
          "镜头景别": "中近景",
          "镜头运动": "缓推",
          "画面内容": "沈云书借酒意和近身优势，继续把筹码加码到自己身上。",
          "人物动作/神态": "她笑得很美，也很盲目，完全没有意识到局势已经在失控边缘。",
          "台词对白": "沈云书：只要公子陪我春宵一刻，莫说往生木，就算是我，也归你所有……",
          "角色": "沈云书",
          "音效": "尾音拉长，环境声几乎静止"
        },
        {
          "分组": "第5组",
          "15秒段": "64.2-81.2秒",
          "镜头号": 50,
          "时长(s)": 0.9,
          "起始时间": 80.3,
          "结束时间": 81.2,
          "场景/时间": "1-1 日 / 外 / 沈家赤木游舫",
          "镜头景别": "近特写",
          "镜头运动": "静止后微压",
          "画面内容": "段青莲眼底的笑意忽然变得薄而冷，像某个开关被彻底拨到另一端。",
          "人物动作/神态": "不给台词，只用眼神完成从“暧昧”到“杀意”的过渡，为下一组爆点蓄势。",
          "台词对白": "—",
          "角色": "段青莲",
          "音效": "低频轰鸣入场"
        },
        {
          "分组": "第6组",
          "15秒段": "81.2-95.7秒",
          "镜头号": 51,
          "时长(s)": 1,
          "起始时间": 81.2,
          "结束时间": 82.2,
          "场景/时间": "1-1 日 / 外 / 湖面群船",
          "镜头景别": "中景",
          "镜头运动": "环境停顿式定镜",
          "画面内容": "湖面、船身、围观人群仿佛集体顿了一拍，空气突然发紧。",
          "人物动作/神态": "这一镜用“异常安静”制造即将翻车的前兆，让观众先于角色感到不对劲。",
          "台词对白": "—",
          "角色": "群像",
          "音效": "音乐抽空，只剩雨声与木船轻响"
        },
        {
          "分组": "第6组",
          "15秒段": "81.2-95.7秒",
          "镜头号": 52,
          "时长(s)": 0.7,
          "起始时间": 82.2,
          "结束时间": 82.9,
          "场景/时间": "1-1 日 / 外 / 李娇娇所在画舫",
          "镜头景别": "插入特写",
          "镜头运动": "声音先行+快速切",
          "画面内容": "一声突兀尖叫刺破气氛，先声夺人，不先给来源。",
          "人物动作/神态": "用声音把“突然一声尖叫声传入李娇娇耳中”落地，形成惊吓点。",
          "台词对白": "—",
          "角色": "未知人声（画外）",
          "音效": "尖叫声骤起"
        },
        {
          "分组": "第6组",
          "15秒段": "81.2-95.7秒",
          "镜头号": 53,
          "时长(s)": 0.8,
          "起始时间": 82.9,
          "结束时间": 83.7,
          "场景/时间": "1-1 日 / 外 / 李娇娇所在画舫",
          "镜头景别": "近景",
          "镜头运动": "反应切",
          "画面内容": "李娇娇猛地一怔，耳朵和视线同时被拽回现场。",
          "人物动作/神态": "她从嫌弃旁观者状态瞬间切入“出事了”的警觉状态。",
          "台词对白": "—",
          "角色": "李娇娇",
          "音效": "短促吸气声"
        },
        {
          "分组": "第6组",
          "15秒段": "81.2-95.7秒",
          "镜头号": 54,
          "时长(s)": 0.8,
          "起始时间": 83.7,
          "结束时间": 84.5,
          "场景/时间": "1-1 日 / 外 / 李娇娇所在画舫",
          "镜头景别": "中景",
          "镜头运动": "甩镜跟拍",
          "画面内容": "镜头跟着李娇娇迅速转身看向尖叫来源。",
          "人物动作/神态": "动作果断、幅度大，制造视线被强行扯回的冲击感。",
          "台词对白": "—",
          "角色": "李娇娇",
          "音效": "甩镜风声"
        },
        {
          "分组": "第6组",
          "15秒段": "81.2-95.7秒",
          "镜头号": 55,
          "时长(s)": 1.2,
          "起始时间": 84.5,
          "结束时间": 85.7,
          "场景/时间": "1-1 日 / 外 / 李娇娇主观视角",
          "镜头景别": "主观镜头",
          "镜头运动": "急推到邻船",
          "画面内容": "李娇娇视角穿过雨幕与船栏，迅速锁定沈家游舫。",
          "人物动作/神态": "观众视线被主观镜头带着撞向真相，形成揭示前的最后半拍。",
          "台词对白": "—",
          "角色": "李娇娇",
          "音效": "心跳鼓点+雨声"
        },
        {
          "分组": "第6组",
          "15秒段": "81.2-95.7秒",
          "镜头号": 56,
          "时长(s)": 3.5,
          "起始时间": 85.7,
          "结束时间": 89.2,
          "场景/时间": "1-1 日 / 外 / 沈家赤木游舫",
          "镜头景别": "中近景",
          "镜头运动": "定住冲击画面",
          "画面内容": "段青莲正掐住沈云书的脖子将她提了起来，前一秒的暧昧在这一秒彻底翻面。",
          "人物动作/神态": "段青莲神情冷厉近乎无波，沈云书身体悬空，危险感瞬间拉满。",
          "台词对白": "—",
          "角色": "段青莲/沈云书",
          "音效": "尖叫余波、喉间窒息声"
        },
        {
          "分组": "第6组",
          "15秒段": "81.2-95.7秒",
          "镜头号": 57,
          "时长(s)": 1,
          "起始时间": 89.2,
          "结束时间": 90.2,
          "场景/时间": "1-1 日 / 外 / 沈家赤木游舫",
          "镜头景别": "特写",
          "镜头运动": "快速插切",
          "画面内容": "沈云书痛苦地抓住段青莲的手挣扎，手指用力到发白。",
          "人物动作/神态": "特写只给“抓、掐、挣扎”三件事，暴力感要狠、准、短。",
          "台词对白": "—",
          "角色": "沈云书/段青莲",
          "音效": "挣扎声、指甲刮擦声"
        },
        {
          "分组": "第6组",
          "15秒段": "81.2-95.7秒",
          "镜头号": 58,
          "时长(s)": 1.8,
          "起始时间": 90.2,
          "结束时间": 92,
          "场景/时间": "1-1 日 / 外 / 湖面群船",
          "镜头景别": "群像全景",
          "镜头运动": "摇镜扫过",
          "画面内容": "四周画舫上的贵女们大乱，有人尖叫后退，有人惊呆失语，整个湖面秩序瞬间崩掉。",
          "人物动作/神态": "把“疯批反派”第一次显形拍成公共事件，形成段青莲人物反差的最大声量。",
          "台词对白": "—",
          "角色": "贵女群像",
          "音效": "连续尖叫、骚动声"
        },
        {
          "分组": "第6组",
          "15秒段": "81.2-95.7秒",
          "镜头号": 59,
          "时长(s)": 1,
          "起始时间": 92,
          "结束时间": 93,
          "场景/时间": "1-1 日 / 外 / 李娇娇所在画舫",
          "镜头景别": "近特写",
          "镜头运动": "切回反应",
          "画面内容": "李娇娇眼睛骤然瞪大，脸上写满“我没看错吧”。",
          "人物动作/神态": "她终于亲眼见到“杀人如麻的疯批反派”这一标签的真实质感。",
          "台词对白": "—",
          "角色": "李娇娇",
          "音效": "心跳声一下顶上来"
        },
        {
          "分组": "第6组",
          "15秒段": "81.2-95.7秒",
          "镜头号": 60,
          "时长(s)": 2.7,
          "起始时间": 93,
          "结束时间": 95.7,
          "场景/时间": "1-1 日 / 外 / 李娇娇所在画舫",
          "镜头景别": "近特写",
          "镜头运动": "定镜留白收尾",
          "画面内容": "镜头稳稳停在李娇娇震惊到失语的脸上，把尾钩留给观众。",
          "人物动作/神态": "她盯着对面船上的暴力画面，惊讶、错愕、无语混成一个短促而有效的结尾表情。",
          "台词对白": "李娇娇（惊讶）：我去？",
          "角色": "李娇娇",
          "音效": "环境混乱声做底，台词落尾"
        }
      ]
    },
    {
      "title": "分组统计",
      "rows": 11,
      "cols": 7,
      "header": [
        "分组",
        "时间区间",
        "镜头数",
        "组时长(s)",
        "时长校验",
        "节奏重点",
        "调整依据"
      ],
      "data": [
        {
          "分组": "第1组",
          "时间区间": "0-16.5秒",
          "镜头数": 10,
          "组时长(s)": 16.5,
          "时长校验": "达标（90-120秒内）",
          "节奏重点": "开场氛围+首次系统警告",
          "调整依据": "系统警告台词偏长，留惊愕反应"
        },
        {
          "分组": "第2组",
          "时间区间": "16.5-33.1秒",
          "镜头数": 10,
          "组时长(s)": 16.6,
          "时长校验": "达标（90-120秒内）",
          "节奏重点": "长OS信息灌入+沈家船登场",
          "调整依据": "穿书OS信息量最大，需完整落字"
        },
        {
          "分组": "第3组",
          "时间区间": "33.1-48.7秒",
          "镜头数": 10,
          "组时长(s)": 15.6,
          "时长校验": "达标（90-120秒内）",
          "节奏重点": "反派亮相+目标锁定+第一轮对视",
          "调整依据": "段青莲亮相与李娇娇判断需停顿"
        },
        {
          "分组": "第4组",
          "时间区间": "48.7-64.2秒",
          "镜头数": 10,
          "组时长(s)": 15.5,
          "时长校验": "达标（90-120秒内）",
          "节奏重点": "公主抱挑逗+喜剧吐槽",
          "调整依据": "邪魅挑逗与吐槽对白需要表演节拍"
        },
        {
          "分组": "第5组",
          "时间区间": "64.2-81.2秒",
          "镜头数": 10,
          "组时长(s)": 17,
          "时长校验": "达标（90-120秒内）",
          "节奏重点": "暧昧试探+交易信息+撩拨升级",
          "调整依据": "沈云书两段长对白+酒液动作镜头需延长"
        },
        {
          "分组": "第6组",
          "时间区间": "81.2-95.7秒",
          "镜头数": 10,
          "组时长(s)": 14.5,
          "时长校验": "达标（90-120秒内）",
          "节奏重点": "尖叫反转+掐颈暴露真面目",
          "调整依据": "反转动作强，收尾反应镜头保留钩子"
        },
        {
          "分组": "总计",
          "时间区间": "全片",
          "镜头数": 60,
          "组时长(s)": 95.7,
          "时长校验": "达标",
          "节奏重点": "60镜头 / 95.7秒 / 情绪驱动节奏版",
          "调整依据": "比原90秒版更贴近实际念白与停顿"
        }
      ]
    }
  ],
  "profile": {
    "source": "C:\\Users\\Administrator\\Downloads\\storyboard_ep1_timing_adjusted.xlsx",
    "target_duration_seconds": 95.7,
    "target_duration_range": [
      90.0,
      120.0
    ],
    "group_count": 6,
    "group_durations": [
      16.5,
      16.6,
      15.6,
      15.5,
      17.0,
      14.5
    ],
    "group_beats": [
      "开场钩子",
      "关系建立",
      "冲突升级",
      "高潮前停顿",
      "高潮",
      "尾钩"
    ],
    "group_style_blocks": [
      {
        "group": 1,
        "beat": "开场钩子",
        "focus": "环境建场、群像期待、目标人物未出场先造势",
        "size_candidates": [
          "中近景",
          "近景",
          "近特写",
          "大全景"
        ],
        "movement_candidates": [
          "航拍俯拍+缓慢下摇",
          "横向平移掠镜",
          "微推",
          "切入定镜"
        ],
        "dialogue_density": "medium",
        "audio_density": "high",
        "audio_focus": "环境声先行，先造世界再给人物",
        "group_name": "第1组",
        "reference_shot_count": 10
      },
      {
        "group": 2,
        "beat": "关系建立",
        "focus": "人物关系、信息补充、视角切换、把目标和处境交代清楚",
        "size_candidates": [
          "中近景",
          "近景",
          "中景",
          "多景别蒙太奇"
        ],
        "movement_candidates": [
          "定镜",
          "跳切+叠化+书页闪回",
          "切回群像",
          "快推"
        ],
        "dialogue_density": "medium",
        "audio_density": "high",
        "audio_focus": "对白和环境音并存，建立叙事基线",
        "group_name": "第2组",
        "reference_shot_count": 10
      },
      {
        "group": 3,
        "beat": "冲突升级",
        "focus": "正反打、规则解释、局势升级、把观众推进冲突中心",
        "size_candidates": [
          "中近景",
          "近特写",
          "双人中景",
          "插入特写"
        ],
        "movement_candidates": [
          "微推",
          "定镜",
          "HUD叠加+轻震",
          "突推"
        ],
        "dialogue_density": "medium",
        "audio_density": "high",
        "audio_focus": "对白驱动，辅以重点音效",
        "group_name": "第3组",
        "reference_shot_count": 10
      },
      {
        "group": 4,
        "beat": "高潮前停顿",
        "focus": "情绪压缩、关键判断、爆发前的短暂停顿",
        "size_candidates": [
          "中景",
          "全景",
          "群像中景",
          "正反打特写"
        ],
        "movement_candidates": [
          "突切+抬镜",
          "环绕半圈",
          "插切群像反应",
          "缓推到极近"
        ],
        "dialogue_density": "medium",
        "audio_density": "high",
        "audio_focus": "收窄环境，给情绪留压强",
        "group_name": "第4组",
        "reference_shot_count": 10
      },
      {
        "group": 5,
        "beat": "高潮",
        "focus": "关键场面爆发、情绪兑现、名台词或动作爆点落地",
        "size_candidates": [
          "近景",
          "中近景",
          "特写",
          "双人近景"
        ],
        "movement_candidates": [
          "插入",
          "慢推",
          "正拍微推",
          "反打定格"
        ],
        "dialogue_density": "medium",
        "audio_density": "high",
        "audio_focus": "动作音效、配乐和对白共同推高潮",
        "group_name": "第5组",
        "reference_shot_count": 10
      },
      {
        "group": 6,
        "beat": "尾钩",
        "focus": "余波、反应、悬念停顿、下一章钩子",
        "size_candidates": [
          "中景",
          "近特写",
          "插入特写",
          "近景"
        ],
        "movement_candidates": [
          "环境停顿式定镜",
          "声音先行+快速切",
          "反应切",
          "甩镜跟拍"
        ],
        "dialogue_density": "medium",
        "audio_density": "high",
        "audio_focus": "先给尾音，再给信息钩子",
        "group_name": "第6组",
        "reference_shot_count": 10
      }
    ],
    "default_shot_count": 10,
    "default_keyframe_count": 4,
    "required_fields": [
      "分组",
      "15秒段",
      "镜头号",
      "时长(s)",
      "起始时间",
      "结束时间",
      "场景/时间",
      "镜头景别",
      "镜头运动",
      "画面内容",
      "人物动作/神态",
      "台词对白",
      "角色",
      "音效"
    ],
    "chapter_requirements": {
      "storyboard_files": [
        "storyboard.json",
        "storyboard.csv",
        "storyboard.xlsx"
      ],
      "video_files": [
        "preview/chapter_preview.mp4",
        "delivery/chapter_final_cut.mp4"
      ],
      "qa_files": [
        "qa/qa_report.md",
        "qa/qa_snapshot.json"
      ],
      "audio_files": [
        "audio/audio_plan.json",
        "audio/voiceover.mp3",
        "audio/ambience.wav"
      ]
    },
    "notes": [
      "单章成片总时长控制在 90-120 秒。",
      "必须保留分组、镜头时长、景别、运镜、对白、角色和音效字段。",
      "允许关键帧少于镜头数，但不允许章节没有完整分镜表和章节视频。"
    ],
    "reference_group_shot_counts": [
      10,
      10,
      10,
      10,
      10,
      10
    ],
    "reference_total_shot_count": 60,
    "default_group_shot_distribution": [
      2,
      2,
      2,
      1,
      2,
      1
    ]
  }
}